pygments_zenburn-0.9.0.dist-info/DESCRIPTION.rst
pygments_zenburn-0.9.0.dist-info/entry_points.txt
pygments_zenburn-0.9.0.dist-info/METADATA
pygments_zenburn-0.9.0.dist-info/pydist.json
pygments_zenburn-0.9.0.dist-info/RECORD
pygments_zenburn-0.9.0.dist-info/top_level.txt
pygments_zenburn-0.9.0.dist-info/WHEEL
zenburn/__init__.py
zenburn/style.py
