Metadata-Version: 2.0
Name: pygments-zenburn
Version: 0.9.0
Summary: Syntax highlighting for Pygments based on the Zenburn theme
Home-page: https://github.com/brolewis/pygments_zenburn
Author: Lewis Franklin
Author-email: lewis.franklin@gmail.com
License: BSD License
Keywords: syntax highlighting
Platform: any
Classifier: License :: OSI Approved :: BSD License
Classifier: Intended Audience :: Developers
Classifier: Intended Audience :: End Users/Desktop
Classifier: Intended Audience :: System Administrators
Classifier: Development Status :: 6 - Mature
Classifier: Programming Language :: Python
Classifier: Programming Language :: Python :: 2
Classifier: Programming Language :: Python :: 3
Classifier: Operating System :: OS Independent
Classifier: Topic :: Text Processing :: Filters
Classifier: Topic :: Utilities
